src/pycountss/__init__.py
src/pycountss/data/__init__.py
src/pycountss/data/flatland.txt
src/pycountss/datasets.py
src/pycountss/plotting.py
src/pycountss/pycountss.py
pycounts312tb-0.3.0.dist-info/LICENSE
pycounts312tb-0.3.0.dist-info/METADATA
pycounts312tb-0.3.0.dist-info/WHEEL
pycounts312tb-0.3.0.dist-info/RECORD
