Metadata-Version: 2.3
Name: pycounts312tb
Version: 0.3.0
Summary: Calculate word counts in a text file!
License: MIT
Author: Tomas Beuzen
Requires-Python: >=3.12
Classifier: License :: OSI Approved :: MIT License
Classifier: Programming Language :: Python :: 3
Classifier: Programming Language :: Python :: 3.12
Classifier: Programming Language :: Python :: 3.13
Requires-Dist: matplotlib (>=3.10.0)
